ir_metric/__init__.py
ir_metric/metric.py
ir_metric-0.1.4.dist-info/LICENSE
ir_metric-0.1.4.dist-info/METADATA
ir_metric-0.1.4.dist-info/WHEEL
ir_metric-0.1.4.dist-info/RECORD
