Metadata-Version: 2.1
Name: ir-metric
Version: 0.1.4
Summary: ir_metrics is a Python package designed to facilitate information retrieval (IR) metric calculations. It provides a simple and convenient way to compute various metrics commonly used in IR evaluation.
Home-page: https://github.com/harshkumarchourasia/ir_metric
Author: harshkumarchourasia
Author-email: harshkumarchourasia@gmail.com
Requires-Python: >=3.9,<4.0
Classifier: Programming Language :: Python :: 3
Classifier: Programming Language :: Python :: 3.9
Classifier: Programming Language :: Python :: 3.10
Classifier: Programming Language :: Python :: 3.11
Classifier: Programming Language :: Python :: 3.12
Project-URL: Repository, https://github.com/harshkumarchourasia/ir_metric
